lightning/__init__.py
lightning/lightning.py
lightning/plugin.py
lightning/test_plugin.py
pylightning-0.0.7.3.data/scripts/lightning-pay
pylightning-0.0.7.3.dist-info/METADATA
pylightning-0.0.7.3.dist-info/WHEEL
pylightning-0.0.7.3.dist-info/top_level.txt
pylightning-0.0.7.3.dist-info/zip-safe
pylightning-0.0.7.3.dist-info/RECORD
