Metadata-Version: 2.1
Name: pylightning
Version: 0.0.7.3
Summary: Client library for lightningd
Home-page: http://github.com/ElementsProject/lightning
Author: Christian Decker
Author-email: decker.christian@gmail.com
License: MIT
Platform: UNKNOWN
